LICENSE
MANIFEST.in
README.md
setup.cfg
setup.py
django_rehive_extras/__init__.py
django_rehive_extras/apps.py
django_rehive_extras/exceptions.py
django_rehive_extras/expressions.py
django_rehive_extras/fields.py
django_rehive_extras/filters.py
django_rehive_extras/mixins.py
django_rehive_extras/models.py
django_rehive_extras.egg-info/PKG-INFO
django_rehive_extras.egg-info/SOURCES.txt
django_rehive_extras.egg-info/dependency_links.txt
django_rehive_extras.egg-info/requires.txt
django_rehive_extras.egg-info/top_level.txt
django_rehive_extras/utils/__init__.py
django_rehive_extras/utils/copy.py